 [
      {
        "id": "1",
        "option": "burger",
        "name": "CARNE",  
        "price": "2500",
        "images": "https://github.com/mailys50/SCL016-burger-queen/blob/develop4/src/asset/img/burger.png?raw=true",
        "text": "L-T-P",
        "url": "burger-carne"
      },
      {
        "id": "2",
        "option": "burger",
        "name": "DOBLE CARNE",
        "price": "3500",
        "images":"https://github.com/mailys50/SCL016-burger-queen/blob/develop4/src/asset/img/burger.png?raw=true",
        "text": "L-T-P-Q",
        "url": "burger-doble-carne"
      },
      {
        "id": "3",
        "option": "burger",
        "name": "CARNE Y TOCINO",
        "price": "3000",
        "images": "https://github.com/mailys50/SCL016-burger-queen/blob/develop4/src/asset/img/burger.png?raw=true",
        "text": "L-T-P-Q",
        "url": "burger-carne-tocino"
        
      },
      {
        "id": "4",
        "option": "burger",
        "name": "CARNE Y POLLO",
        "price": "3500",
        "images": "https://github.com/mailys50/SCL016-burger-queen/blob/develop4/src/asset/img/burgerMaxi.png?raw=true",
        "text": "L-T-P-Q-J",
        "url": "burger-carne-pollo"
        
      },
      {
        "id": "5",
        "option": "burger",
        "name": "POLLO",
        "price": "2500",
        "images": "https://github.com/mailys50/SCL016-burger-queen/blob/develop4/src/asset/img/burgerPollo.png?raw=true",
        "text": "L-T-P-S",
        "url": "burger-carne-pollo"
        
      },
     
      {
        "id": "6",
        "option": "burger",
        "name": "DOBLE POLLO",
        "price": "3500",
        "images":"https://github.com/mailys50/SCL016-burger-queen/blob/develop4/src/asset/img/burgerPollo.png?raw=true",
        "text": "L-T-P-S-Q",
        "url": "burger-doble-pollo"
        
      },
      {
        "id": "7",
        "option": "burger",
        "name": "POLLO Y TOCINO",
        "price": "3500",
        "images": "https://github.com/mailys50/SCL016-burger-queen/blob/develop4/src/asset/img/burgerPollo.png?raw=true",
        "text": "L-T-P-S-Q",
        "url": "burger-pollo-tocino"
        
      },
      {
        "id": "8",
        "option": "burger",
        "name": "MAXI",
        "price": "4000",
        "images":"https://github.com/mailys50/SCL016-burger-queen/blob/develop4/src/asset/img/burgerMaxi.png?raw=true",
        "text": "L-T-P-S-Q-J-H",
        "url": "burger-pollo-tocino"
        
      },
      {
        "id": "9",
        "option": "shawarma",
        "name": "CARNE",  
        "price": "2500",
        "images":"https://github.com/mailys50/SCL016-burger-queen/blob/develop4/src/asset/img/shawarma.png?raw=true",
        "url": "shawarma-carne"
      },
      
      {
        "id": "10",
        "option": "shawarma",
        "name": "POLLO",
        "price": "2500",
        "images": "https://github.com/mailys50/SCL016-burger-queen/blob/develop4/src/asset/img/shawarma.png?raw=true",
        "url": "shawarma-pollo"
        
      },
     
      {
        "id": "11",
        "option": "shawarma",
        "name": "MAXI",
        "price": "4000",
        "images": "https://github.com/mailys50/SCL016-burger-queen/blob/develop4/src/asset/img/shawarma.png?raw=true",
        "url": "shawarma-maxi"
        
        
      },{
        "id": "12",
        "option": "drink",
        "name": "PIÑA",
        "price": "1500",
        "images":"https://github.com/mailys50/SCL016-burger-queen/blob/develop4/src/asset/img/pi%C3%B1a.png?raw=true",
        "text": "500 ml",
        "url": "drink-piña"
        
      },
      {
          "id": "13",
          "option": "drink",
          "name": "NARANJA",
          "price": "1500",
          "images":"https://github.com/mailys50/SCL016-burger-queen/blob/develop4/src/asset/img/naranja.png?raw=true",
          "text": "500 ml",
          "url": "drink-naranja"
      },
      {
          "id": "14",
          "option": "drink",
          "name": "FRESA",
          "price": "1500",
          "images":"https://github.com/mailys50/SCL016-burger-queen/blob/develop4/src/asset/img/fresa.png?raw=true",
          "text": "500 ml",
          "url": "drink-fresa"
        
      },
    {
        "id": "15",
        "option": "drink",
        "name": "FRAMBUESA",
        "price": "1500",
        "images":"https://github.com/mailys50/SCL016-burger-queen/blob/develop4/src/asset/img/framb.png?raw=true",
        "text": "500 ml",
        "url": "drink-frambuesa"
    },
    {
        "id": "16",
        "option": "drink",
        "name": "COCA COLA",
        "price": "1000",
        "images":"https://github.com/mailys50/SCL016-burger-queen/blob/develop4/src/asset/img/cocaCola.png?raw=true",
        "text": "500 ml",
        "url": "drink-coca-cola"
    },
    {
      
        "id": "17",
        "option": "drink",
        "name": "FANTA",
        "price": "1000",
        "images":"https://github.com/mailys50/SCL016-burger-queen/blob/develop4/src/asset/img/fanta.png?raw=true",
        "text": "500 ml",
        "url": "drink-fanta"
      
    },
    {
        "id": "18",
        "option": "drink",
        "name": "SPRITE",
        "price": "1000",
        "images":"https://github.com/mailys50/SCL016-burger-queen/blob/develop4/src/asset/img/sprite.png?raw=true",
        "text": "500 ml",
        "url": "drink-sprinte"
    },
    {
      
        "id": "19",
        "option": "drink",
        "name": "COCA COLA",
        "price": "1500",
        "images":"https://github.com/mailys50/SCL016-burger-queen/blob/develop4/src/asset/img/cocaCola2.png?raw=true",
        "text": "2 lts",
        "url": "drink-coca-cola-dos-litros"
      
    }
   
    
     
    ]
  